{
  "title": {
    "zh": "维度切换组件",
    "en": "Switcher"
  },
  "demos": [
    {
      "filename": "pivot.tsx",
      "title": {
        "zh": "交叉表维度切换",
        "en": "Switcher in pivot sheet"
      },
      "screenshot": "https://gw.alipayobjects.com/zos/antfincdn/KJWa1WHyF/7e5f6a82-9148-411d-826c-b361d30258cc.png"
    },
    {
      "filename": "pivot-with-children.tsx",
      "title": {
        "zh": "交叉表子维度切换",
        "en": "Switcher with children in pivot sheet"
      },
      "screenshot": "https://gw.alipayobjects.com/zos/antfincdn/DHwIeV3Z3/10c6b7a6-b4ec-40af-ad22-a9c4d1d1fa55.png"
    },
    {
      "filename": "table.tsx",
      "title": {
        "zh": "明细表维度切换",
        "en": "Switcher in table sheet"
      },
      "screenshot": "https://gw.alipayobjects.com/zos/antfincdn/1G3F4i7rU/bd9f14a3-06da-4c5b-9e3d-d63ab5ee61e4.png"
    }
  ]
}
